isSymbols/__init__.py
isSymbols/isSymbols.py
issymbols_h4rck4n0-0.1.5.dist-info/METADATA
issymbols_h4rck4n0-0.1.5.dist-info/WHEEL
issymbols_h4rck4n0-0.1.5.dist-info/top_level.txt
issymbols_h4rck4n0-0.1.5.dist-info/RECORD
