Metadata-Version: 2.4
Name: isSymbols-h4rck4n0
Version: 0.1.5
Summary: script che controlla se ci sono simboli in una stringa
Home-page: 
Author: h4rck4n0
Dynamic: author
Dynamic: description
Dynamic: description-content-type
Dynamic: summary
